fluidsolve/___version.py
fluidsolve/__init__.py
fluidsolve/__main__.py
fluidsolve/_matplotlib.ico
fluidsolve/aux_tools.py
fluidsolve/catalogue.py
fluidsolve/comp_base.py
fluidsolve/comp_pump.py
fluidsolve/comp_resist.py
fluidsolve/core.py
fluidsolve/medium.py
fluidsolve/network.py
fluidsolve/plotext.py
fluidsolve/plotlib.py
fluidsolve/util.py
fluidsolve/wpoint.py
fluidsolve/comp_cat/_readme.txt
fluidsolve/comp_cat/cat_app_b_bl45.json
fluidsolve/comp_cat/cat_app_b_bl5_90.json
fluidsolve/comp_cat/cat_app_b_bl90.json
fluidsolve/comp_cat/cat_app_b_bs180.json
fluidsolve/comp_cat/cat_app_b_bs45.json
fluidsolve/comp_cat/cat_app_b_bs90.json
fluidsolve/comp_cat/cat_app_t_rts.json
fluidsolve/comp_cat/cat_app_t_tk.json
fluidsolve/comp_cat/cat_app_t_ts.json
fluidsolve/comp_cat/cat_pipe_nw.json
fluidsolve/comp_cat/cat_pipe_sds.json
fluidsolve/comp_cat/cat_pump_c_apv.json
fluidsolve-0.7.0.dist-info/licenses/LICENSE
x_examples/__init__.py
x_examples/a00_test.py
x_examples/e00_fluids.py
x_examples/e01_basic.py
x_examples/e02_basic.py
x_examples/e03_serial.py
x_examples/e04_cat.py
x_examples/e05_medium.py
x_examples/e06_orifice.py
x_examples/e07_exitflow.py
x_examples/e10_plot.py
x_examples/e11_plot.py
x_examples/e12_plot.py
x_examples/e13_pump_rpm.py
x_examples/e20_pump_serial.py
x_examples/e21_pump_serial.py
x_examples/e22_pump_parallel.py
x_examples/e30_basic.py
x_examples/e50_plot.py
x_tests/__init__.py
x_tests/test_medium.py
x_tools/__init__.py
x_tools/gen_examples_tests.py
x_tools/gen_ini.py
x_tools/test2.py
fluidsolve-0.7.0.dist-info/METADATA
fluidsolve-0.7.0.dist-info/WHEEL
fluidsolve-0.7.0.dist-info/top_level.txt
fluidsolve-0.7.0.dist-info/RECORD
