Metadata-Version: 2.4
Name: FluidSolve
Version: 0.7.0
Summary: Fluid Dynamics Calculations
Author-email: DOSprojects <mail@domain.com>
License: MIT License
Project-URL: homepage, https://github.com/DOSprojects/fluidsolve.git
Project-URL: documentation, https://fluidsolve.readthedocs.io/en/latest/index.html
Project-URL: repository, https://github.com/DOSprojects/fluidsolve.git
Project-URL: changelog, https://github.com/DOSprojects/fluidsolve/blob/main/CHANGELOG.rst
Keywords: python,fluid dynamics,engineering,physics,pint,fluids,calculation,process engineering,mechanical engineering
Classifier: Development Status :: 3 - Alpha
Classifier: Environment :: Console
Classifier: License :: OSI Approved :: MIT License
Classifier: Operating System :: OS Independent
Classifier: Programming Language :: Python
Classifier: Topic :: Education
Classifier: Topic :: Scientific/Engineering :: Physics
Requires-Python: >=3.10
License-File: LICENSE
Requires-Dist: numpy
Requires-Dist: matplotlib
Requires-Dist: mpl_interactions
Requires-Dist: fluids
Requires-Dist: pint
Requires-Dist: thermo
Requires-Dist: scipy
Provides-Extra: dev
Requires-Dist: pylint; extra == "dev"
Requires-Dist: build; extra == "dev"
Requires-Dist: twine; extra == "dev"
Provides-Extra: doc
Requires-Dist: sphinx; extra == "doc"
Requires-Dist: sphinx-rtd-theme; extra == "doc"
Requires-Dist: sphinx-gallery; extra == "doc"
Requires-Dist: sphinx-toolbox; extra == "doc"
Requires-Dist: docutils==0.20; extra == "doc"
Provides-Extra: test
Requires-Dist: pytest; extra == "test"
Dynamic: license-file
